[[{"isTitle": true, "value": "Photograph, Muhammad Ali and Alonzo Johnson"}, {"isImage": true, "value": "https://dgcollectiondevstg.blob.core.windows.net/media/images/QOSM.2017.0003.width-180_uGRosTv.jpg"}, {"label": "Object Number", "value": "QM.2017.0003"}, {"label": "Year acquired", "value": "1971"}, {"label": "Country of origin", "value": "Qatar"}, {"label": "Latitude", "value": "25.3336984"}, {"label": "Longitude", "value": "51.2295295"}, {"label": "Collection", "value": "3-2-1 Qatar Olympic and Sports Museum"}]]